{"version":1,"resource":"file:///home/virtuoso/Programming/UWT/DB/Language_Website/src/components/List.js","entries":[{"id":"5ICd.js","timestamp":1654985521183},{"id":"xvq1.js","timestamp":1654985559966},{"id":"xy3P.js","timestamp":1654985576033},{"id":"KPwt.js","timestamp":1654985962626},{"id":"lV1y.js","timestamp":1654986408860},{"id":"826Q.js","timestamp":1654994901072},{"id":"fqDt.js","timestamp":1654994924005},{"id":"NRVP.js","timestamp":1654994942259},{"id":"t9Ug.js","timestamp":1654994952389},{"id":"mwMW.js","timestamp":1654995012009},{"id":"jfnY.js","source":"undoRedo.source","timestamp":1654995190739},{"id":"nDmO.js","timestamp":1654995196722},{"id":"vJli.js","timestamp":1654995332075},{"id":"CFUT.js","timestamp":1654995476682},{"id":"t04E.js","timestamp":1654995487685},{"id":"E6NT.js","timestamp":1654995706789},{"id":"5ZVU.js","timestamp":1654995821379},{"id":"RW1U.js","timestamp":1654996011965},{"id":"VpcI.js","timestamp":1654996064359}]}